pyhub_pr/__init__.py
pyhub_pr/__main__.py
pyhub_pr/_git.py
pyhub_pr/pyhub_pr.py
pyhub_pr-0.1.0.dist-info/LICENSE
pyhub_pr-0.1.0.dist-info/METADATA
pyhub_pr-0.1.0.dist-info/WHEEL
pyhub_pr-0.1.0.dist-info/entry_points.txt
pyhub_pr-0.1.0.dist-info/top_level.txt
pyhub_pr-0.1.0.dist-info/RECORD
