Metadata-Version: 2.1
Name: pyhub-pr
Version: 0.1.0
Summary: Will create an issue from the command line with given parameters
Home-page: https://github.com/seluj78/pyhub_pr
Author: Jules Lasne
Author-email: jules.lasne@gmail.com
License: MIT license
Keywords: pyhub_pr
Platform: UNKNOWN
Classifier: Development Status :: 2 - Pre-Alpha
Classifier: Intended Audience :: Developers
Classifier: License :: OSI Approved :: MIT License
Classifier: Natural Language :: English
Classifier: Programming Language :: Python :: 3
Classifier: Programming Language :: Python :: 3.5
Classifier: Programming Language :: Python :: 3.6
Classifier: Programming Language :: Python :: 3.7
Requires-Dist: requests
